odoo/addons/stock_picking_batch_start/README.rst
odoo/addons/stock_picking_batch_start/__init__.py
odoo/addons/stock_picking_batch_start/__manifest__.py
odoo/addons/stock_picking_batch_start/i18n/stock_picking_batch_start.pot
odoo/addons/stock_picking_batch_start/models/__init__.py
odoo/addons/stock_picking_batch_start/models/stock_picking.py
odoo/addons/stock_picking_batch_start/models/stock_picking_batch.py
odoo/addons/stock_picking_batch_start/readme/CONTRIBUTORS.rst
odoo/addons/stock_picking_batch_start/readme/DESCRIPTION.rst
odoo/addons/stock_picking_batch_start/static/description/icon.png
odoo/addons/stock_picking_batch_start/static/description/index.html
odoo/addons/stock_picking_batch_start/tests/__init__.py
odoo/addons/stock_picking_batch_start/tests/test_stock_picking_batch_start.py
odoo/addons/stock_picking_batch_start/views/stock_picking_batch.xml
odoo_addon_stock_picking_batch_start-16.0.1.0.0.2.dist-info/METADATA
odoo_addon_stock_picking_batch_start-16.0.1.0.0.2.dist-info/WHEEL
odoo_addon_stock_picking_batch_start-16.0.1.0.0.2.dist-info/top_level.txt
odoo_addon_stock_picking_batch_start-16.0.1.0.0.2.dist-info/RECORD
