Metadata-Version: 2.1
Name: odoo-addon-stock_picking_batch_start
Version: 16.0.1.0.0.2
Summary: This module depends on the `stock_picking_start` module, which allows for users to start of all individual pickings through buttons accessible on the batch form view.
Home-page: https://github.com/OCA/stock-logistics-workflow
Author: ACSONE SA/NV,Odoo Community Association (OCA)
Author-email: support@odoo-community.org
License: AGPL-3
Classifier: Programming Language :: Python
Classifier: Framework :: Odoo
Classifier: Framework :: Odoo :: 16.0
Classifier: License :: OSI Approved :: GNU Affero General Public License v3
Requires-Python: >=3.10
Requires-Dist: odoo-addon-stock-picking-start<16.1dev,>=16.0dev
Requires-Dist: odoo<16.1dev,>=16.0a
